fx_sdk/__init__.py
fx_sdk/client.py
fx_sdk/constants.py
fx_sdk/exceptions.py
fx_sdk/utils.py
fx_sdk/abis/convex_base_reward_pool.json
fx_sdk/abis/convex_booster.json
fx_sdk/abis/convex_vault.json
fx_sdk/abis/convex_vault_factory.json
fx_sdk/abis/crv_token.json
fx_sdk/abis/curve_address_provider.json
fx_sdk/abis/curve_factory.json
fx_sdk/abis/curve_gauge.json
fx_sdk/abis/curve_meta_registry.json
fx_sdk/abis/curve_pool.json
fx_sdk/abis/curve_registry.json
fx_sdk/abis/cvxfxn.json
fx_sdk/abis/cvxfxn_deposit.json
fx_sdk/abis/cvxfxn_stake.json
fx_sdk/abis/diamond.json
fx_sdk/abis/erc20.json
fx_sdk/abis/fxn.json
fx_sdk/abis/fxsp.json
fx_sdk/abis/fxusd.json
fx_sdk/abis/fxusd_base_pool.json
fx_sdk/abis/gauge_controller.json
fx_sdk/abis/liquidity_gauge.json
fx_sdk/abis/market.json
fx_sdk/abis/multipath_converter.json
fx_sdk/abis/pool_manager.json
fx_sdk/abis/rebalance_pool.json
fx_sdk/abis/rebalance_pool_registry.json
fx_sdk/abis/reserve_pool.json
fx_sdk/abis/saving_fxusd.json
fx_sdk/abis/steth_gateway.json
fx_sdk/abis/steth_treasury.json
fx_sdk/abis/vefxn.json
fx_sdk/abis/vesting.json
tests/__init__.py
tests/pre_upload_tests.py
tests/quick_test.py
tests/test_address.py
tests/test_convex.py
tests/test_curve.py
tests/test_installation.py
tests/test_installed_package.py
tests/test_sdk.py
tests/tests.py
fx_sdk-0.4.0.dist-info/LICENSE
fx_sdk-0.4.0.dist-info/METADATA
fx_sdk-0.4.0.dist-info/WHEEL
fx_sdk-0.4.0.dist-info/top_level.txt
fx_sdk-0.4.0.dist-info/RECORD
