Metadata-Version: 2.1
Name: fx-sdk
Version: 0.4.0
Summary: A Pythonic SDK for the f(x) Protocol
Home-page: https://github.com/chrisstampar/fx-sdk
Author: Christopher Stampar (@cstampar)
Author-email: Christopher Stampar <cstampar@me.com>
Project-URL: Homepage, https://github.com/chrisstampar/fx-sdk
Project-URL: Documentation, https://fx-sdk.readthedocs.io/en/latest/
Project-URL: Source, https://github.com/chrisstampar/fx-sdk
Project-URL: Bug Tracker, https://github.com/chrisstampar/fx-sdk/issues
Keywords: defi,ethereum,fx-protocol,stablecoin
Classifier: Programming Language :: Python :: 3
Classifier: License :: OSI Approved :: MIT License
Classifier: Operating System :: OS Independent
Requires-Python: >=3.8
License-File: LICENSE
Requires-Dist: web3>=6.0.0
Requires-Dist: eth-account>=0.5.0
Requires-Dist: eth-typing>=3.0.0
Requires-Dist: eth-utils>=2.0.0
Requires-Dist: python-dotenv>=1.0.0
